{
    "id":"5bef666d19b48b5e88ed4ad6",
    "checkItemStates":[],
    "closed":false,
    "dateLastActivity":"2018-12-18T02:08:46.042Z",
    "desc":"I can run code from eclipse in an frc simulator in theory but for some reason it this error comes up so the project can't be built",
    "descData":{"emoji":{}},
    "dueReminder":null,
    "idBoard":"5bee29714a832070b2832fe3",
    "idList":"5bee3886401ee45c03f0b929",
    "idMembersVoted":[],
    "idShort":7,
    "idAttachmentCover":null,
    "idLabels":[],
    "manualCoverAttachment":false,
    "name":"/wpilib/java/current/ant/build.xml:14: No Handler found for ClassLoader jdk.internal.loader.ClassLoaders$AppClassLoader and action org.apache.tools.ant.taskdefs.classloader.ClassLoaderAdapterAction@5562c41e",
    "pos":327679,
    "shortLink":"Y7oRg3Sx",
    "isTemplate":false,
    "cardRole":null,
    "dueComplete":false,
    "due":null,"labels":[],
    "shortUrl":"https://trello.com/c/Y7oRg3Sx",
    "start":null,
    "url":"https://trello.com/c/Y7oRg3Sx/7-wpilib-java-current-ant-buildxml14-no-handler-found-for-classloader-jdkinternalloaderclassloadersappclassloader-and-action-orga",
    "cover":{
        "idAttachment":null,
        "color":null,
        "idUploadedBackground":null,
        "size":"normal",
        "brightness":"light"
    },
    "idMembers":[
        "5b8811c85d2981408fb4ff9b",
        "5b880f6ac74ce968f469b7bb",
        "5bee38ceba8fa1100ffa3af4",
        "5b880f18736d3b3dead937d9"
    ],
    "email":null,
    "idChecklists":[],
    "badges":{
        "attachmentsByType":{
            "trello":{
                "board":0,"card":0
            }
        },
        "location":false,
        "votes":0,
        "viewingMemberVoted":false,
        "subscribed":true,
        "fogbugz":"",
        "checkItems":0,
        "checkItemsChecked":0,
        "checkItemsEarliestDue":null,
        "comments":0,
        "attachments":0,
        "description":true,
        "due":null,
        "dueComplete":false,
        "start":null
    },
    "subscribed":true
}